README
setup.cfg
setup.py
yate/__init__.py
yate/config.py
yate/json_theme_parser.py
yate/project_tree.py
yate/quick_open.py
yate/style.py
yate/syntax.py
yate/tm_theme_parser.py
yate/yate.py
yate.egg-info/PKG-INFO
yate.egg-info/SOURCES.txt
yate.egg-info/dependency_links.txt
yate.egg-info/entry_points.txt
yate.egg-info/not-zip-safe
yate.egg-info/requires.txt
yate.egg-info/top_level.txt