Metadata-Version: 1.0
Name: yate
Version: 0.3dev
Summary: Yet Another Text Editor
Home-page: http://dcestari.github.com/yate
Author: Daniel Cestari
Author-email: dcestari@gmail.com
License: MIT
Platform: UNKNOWN
Classifier: Development Status :: 2 - Pre-Alpha
Classifier: License :: OSI Approved :: MIT License
Classifier: Topic :: Software Development
